<?xml version="1.0" ?>
<GeneralStatistics>
    <Statistic name="count">
        <StatisticMap key="546903" value="5" />
        <StatisticMap key="546969" value="2" />
        <StatisticMap key="547336" value="1" />
        <StatisticMap key="548196" value="5" />
        <StatisticMap key="548197" value="1" />
    </Statistic>
    <Statistic name="max">
        <StatisticMap key="546903" value="[501, 729, 932, 1303, 2027, 2262, 2398, 2666, 2744, 1812, 481, 705, 959, 1340, 1955, 2187, 2299, 2543, 2827, 1859, 514.594, 497.232, 91.4877, 130.348, 5938.45, 5868.63]" />
        <StatisticMap key="546969" value="[531, 774, 900, 1213, 1850, 2140, 2290, 2413, 2648, 1780, 495, 719, 837, 1156, 1740, 2040, 2030, 2299, 2665, 1797, 516.556, 440.227, 80.6056, 140.811, 5663.79, 5427.36]" />
        <StatisticMap key="547336" value="[673, 836, 909, 1084, 1640, 1815, 1531, 2007, 2015, 1445, 653, 851, 918, 1096, 1642, 1780, 1489, 2036, 2036, 1431, 254.918, 237.225, 136.492, 155.177, 4653.73, 4649.15]" />
        <StatisticMap key="548196" value="[810, 1048, 1324, 1250, 2022, 2257, 2472, 2631, 2373, 1615, 861, 1086, 1435, 1274, 1929, 2203, 2366, 2562, 2488, 1639, 619.505, 571.124, 58.2363, 51.0511, 5741.26, 5668.02]" />
        <StatisticMap key="548197" value="[877, 1079, 1310, 1170, 1740, 1919, 1873, 2117, 2095, 1522, 824, 1083, 1327, 1173, 1739, 1879, 1913, 2134, 2126, 1515, 176.877, 180.864, 55.9476, 52.7358, 5140.41, 5154.81]" />
    </Statistic>
    <Statistic name="mean">
        <StatisticMap key="546903" value="[460, 693.2, 875, 1250.8, 1979.8, 2232, 2350.8, 2591.6, 2623.4, 1724.4, 465.2, 681.2, 895.6, 1284.6, 1902.8, 2144, 2250, 2496.2, 2711.6, 1776, 457.742, 430.853, 54.555, 92.8216, 5834.39, 5759.38]" />
        <StatisticMap key="546969" value="[498, 736, 815, 1195, 1848, 2138.5, 2268.5, 2405.5, 2644.5, 1776.5, 464.5, 707.5, 813, 1134, 1726.5, 2032.5, 2005, 2294.5, 2647, 1783.5, 472.291, 422.989, 76.5523, 138.031, 5653.55, 5408.37]" />
        <StatisticMap key="547336" value="[673, 836, 909, 1084, 1640, 1815, 1531, 2007, 2015, 1445, 653, 851, 918, 1096, 1642, 1780, 1489, 2036, 2036, 1431, 254.918, 237.225, 136.492, 155.177, 4653.73, 4649.15]" />
        <StatisticMap key="548196" value="[566.2, 783.2, 966, 1229.8, 1947.2, 2163.8, 2270.4, 2485.6, 2257.2, 1587.2, 551.8, 746.6, 991.4, 1229.8, 1872.2, 2104, 2231.8, 2440.2, 2330.4, 1611.6, 408.848, 393.107, -1.8348, 21.7298, 5566.2, 5517.24]" />
        <StatisticMap key="548197" value="[877, 1079, 1310, 1170, 1740, 1919, 1873, 2117, 2095, 1522, 824, 1083, 1327, 1173, 1739, 1879, 1913, 2134, 2126, 1515, 176.877, 180.864, 55.9476, 52.7358, 5140.41, 5154.81]" />
    </Statistic>
    <Statistic name="min">
        <StatisticMap key="546903" value="[415, 657, 765, 1196, 1945, 2196, 2284, 2506, 2495, 1617, 422, 657, 772, 1243, 1831, 2083, 2175, 2442, 2563, 1663, 420.398, 392.846, 22.1221, 54.2986, 5748.53, 5666.07]" />
        <StatisticMap key="546969" value="[465, 698, 730, 1177, 1846, 2137, 2247, 2398, 2641, 1773, 434, 696, 789, 1112, 1713, 2025, 1980, 2290, 2629, 1770, 428.027, 405.751, 72.499, 135.25, 5643.31, 5389.38]" />
        <StatisticMap key="547336" value="[673, 836, 909, 1084, 1640, 1815, 1531, 2007, 2015, 1445, 653, 851, 918, 1096, 1642, 1780, 1489, 2036, 2036, 1431, 254.918, 237.225, 136.492, 155.177, 4653.73, 4649.15]" />
        <StatisticMap key="548196" value="[332, 531, 554, 1211, 1817, 1979, 1981, 2213, 2144, 1561, 299, 483, 603, 1184, 1785, 1919, 2054, 2210, 2196, 1560, 198.79, 177.415, -20.4334, -9.24882, 5348.7, 5417.04]" />
        <StatisticMap key="548197" value="[877, 1079, 1310, 1170, 1740, 1919, 1873, 2117, 2095, 1522, 824, 1083, 1327, 1173, 1739, 1879, 1913, 2134, 2126, 1515, 176.877, 180.864, 55.9476, 52.7358, 5140.41, 5154.81]" />
    </Statistic>
    <Statistic name="std">
        <StatisticMap key="546903" value="[30.5041, 25.5578, 64.082, 40.2641, 30.7197, 25.7002, 45.3398, 59.7185, 99.7211, 71.6156, 24.366, 20.8854, 71.7029, 44.6072, 46.0673, 39.3573, 58.0172, 37.8312, 101.786, 74.4043, 35.0812, 40.1216, 27.4513, 29.1194, 84.0096, 87.528]" />
        <StatisticMap key="546969" value="[46.669, 53.7401, 120.208, 25.4558, 2.82843, 2.12132, 30.4056, 10.6066, 4.94975, 4.94975, 43.1335, 16.2635, 33.9411, 31.1127, 19.0919, 10.6066, 35.3553, 6.36396, 25.4558, 19.0919, 62.5999, 24.3784, 5.73222, 3.93235, 14.4857, 26.8597]" />
        <StatisticMap key="547336" value="[-nan, -nan, -nan, -nan, -nan, -nan, -nan, -nan, -nan, -nan, -nan, -nan, -nan, -nan, -nan, -nan, -nan, -nan, -nan, -nan, -nan, -nan, -nan, -nan, -nan, -nan]" />
        <StatisticMap key="548196" value="[182.586, 192.727, 301.105, 15.8651, 82.0226, 114.13, 183.84, 167.18, 83.1667, 23.4776, 207.356, 222.473, 302.873, 34.6439, 53.4949, 111.962, 116.098, 138.218, 107.876, 31.6749, 164.205, 144.306, 33.858, 22.1671, 149.686, 109.043]" />
        <StatisticMap key="548197" value="[-nan, -nan, -nan, -nan, -nan, -nan, -nan, -nan, -nan, -nan, -nan, -nan, -nan, -nan, -nan, -nan, -nan, -nan, -nan, -nan, -nan, -nan, -nan, -nan, -nan, -nan]" />
    </Statistic>
</GeneralStatistics>
